README
setup.cfg
setup.py
./gridspec_api/axis/nccf_add_axis_att.c
./gridspec_api/axis/nccf_def_axis.c
./gridspec_api/axis/nccf_def_axis_from_file.c
./gridspec_api/axis/nccf_free_axis.c
./gridspec_api/axis/nccf_get_axis_datapointer.c
./gridspec_api/axis/nccf_inq_axis_datatype.c
./gridspec_api/axis/nccf_inq_axis_len.c
./gridspec_api/axis/nccf_inq_axis_name.c
./gridspec_api/axis/nccf_put_axis.c
./gridspec_api/coord/nccf_add_coord_att.c
./gridspec_api/coord/nccf_def_coord.c
./gridspec_api/coord/nccf_def_coord_from_axes.c
./gridspec_api/coord/nccf_def_coord_from_file.c
./gridspec_api/coord/nccf_free_coord.c
./gridspec_api/coord/nccf_get_coord_data_pointer.c
./gridspec_api/coord/nccf_inq_coord_bound.c
./gridspec_api/coord/nccf_inq_coord_bound_slice.c
./gridspec_api/coord/nccf_inq_coord_dimnames.c
./gridspec_api/coord/nccf_inq_coord_dims.c
./gridspec_api/coord/nccf_inq_coord_name.c
./gridspec_api/coord/nccf_inq_coord_ndims.c
./gridspec_api/coord/nccf_inq_coord_units.c
./gridspec_api/coord/nccf_is_coord.c
./gridspec_api/coord/nccf_put_coord.c
./gridspec_api/data/nccf_add_data_att.c
./gridspec_api/data/nccf_def_data.c
./gridspec_api/data/nccf_def_data_from_file.c
./gridspec_api/data/nccf_free_data.c
./gridspec_api/data/nccf_get_data_pointer.c
./gridspec_api/data/nccf_inq_data_dims.c
./gridspec_api/data/nccf_inq_data_gridid.c
./gridspec_api/data/nccf_inq_data_ndims.c
./gridspec_api/data/nccf_inq_data_type.c
./gridspec_api/data/nccf_put_data.c
./gridspec_api/data/nccf_set_data.c
./gridspec_api/global/nccf_add_global_att.c
./gridspec_api/global/nccf_def_global.c
./gridspec_api/global/nccf_def_global_from_file.c
./gridspec_api/global/nccf_free_global.c
./gridspec_api/global/nccf_inq_global_att.c
./gridspec_api/global/nccf_inq_global_attval.c
./gridspec_api/global/nccf_inq_global_natts.c
./gridspec_api/global/nccf_put_global.c
./gridspec_api/grid/nccf_def_grid.c
./gridspec_api/grid/nccf_def_grid_from_file.c
./gridspec_api/grid/nccf_detect_grid_periodicity.c
pycf.egg-info/PKG-INFO
pycf.egg-info/SOURCES.txt
pycf.egg-info/dependency_links.txt
pycf.egg-info/top_level.txt
