Metadata-Version: 1.1
Name: pycf
Version: 1.6.8
Summary: Python access to the LibCF library
Home-page: http://www.unidata.ucar.edu/software/libcf/
Author: UNKNOWN
Author-email: alexander.pletzer@nesi.org.nz
License: UCAR/Unidata
Download-URL: http://python.org/pypi/pylibcf
Platform: any
